ssg/__init__.py
ssg/featurizer.py
ssg/artifacts/crf3_mix.crfsuite2
ssg-0.0.8.data/scripts/ssg-cli
ssg-0.0.8.dist-info/LICENSE
ssg-0.0.8.dist-info/METADATA
ssg-0.0.8.dist-info/WHEEL
ssg-0.0.8.dist-info/top_level.txt
ssg-0.0.8.dist-info/RECORD
