Metadata-Version: 1.1
Name: ssg
Version: 0.0.8
Summary: Thai syllable segmentation using Conditional Random Fields
Home-page: https://github.com/ponrawee/ssg
Author: Ponrawee Prasertsom
Author-email: ponrawee.pra@gmail.com
License: Apache Software License 2.0
Download-URL: https://github.com/ponrawee/ssg.git
Keywords: crf,syllable,tokenization,thai
Platform: UNKNOWN
Classifier: Development Status :: 3 - Alpha
Classifier: License :: OSI Approved :: Apache Software License
Classifier: Natural Language :: Thai
Classifier: Topic :: Text Processing
Classifier: Topic :: Text Processing :: General
Classifier: Topic :: Text Processing :: Linguistic
